cchess/__init__.py
cchess/__main__.py
cchess/board.py
cchess/common.py
cchess/engine.py
cchess/exception.py
cchess/game.py
cchess/move.py
cchess/piece.py
cchess/read_cbf.py
cchess/read_cbr.py
cchess/read_pgn.py
cchess/read_txt.py
cchess/read_xqf.py
cchess/zhash_data.py
cchess-1.25.5.dist-info/licenses/LICENSE
cchess-1.25.5.dist-info/METADATA
cchess-1.25.5.dist-info/WHEEL
cchess-1.25.5.dist-info/RECORD
