Metadata-Version: 2.4
Name: cchess
Version: 1.25.5
Summary: ChineseChess (AKA XiangQi) library
License: LGPL-3.0-or-later
License-File: LICENSE
Keywords: XiangQi,Xiang Qi,ChineseChess
Author: walker8088
Author-email: walker8088@gmail.com
Requires-Python: >=3.6
Classifier: Intended Audience :: Developers
Classifier: Topic :: Software Development :: Libraries :: Python Modules
Classifier: Operating System :: MacOS :: MacOS X
Classifier: Operating System :: POSIX
Classifier: Operating System :: POSIX :: BSD
Classifier: Operating System :: POSIX :: Linux
Classifier: Operating System :: Microsoft :: Windows
Classifier: Programming Language :: Python
Classifier: Programming Language :: Python :: 3
Classifier: Programming Language :: Python :: 3 :: Only
Classifier: Programming Language :: Python :: Implementation :: CPython
Project-URL: Homepage, https://github.com/walker8088/cchess
Project-URL: Source, https://github.com/walker8088/cchess
